bigninja/__init__.py
bigninja/dataframe.py
tests/__init__.py
tests/test_dataframe.py
bigninja-0.0.3.dist-info/LICENSE
bigninja-0.0.3.dist-info/METADATA
bigninja-0.0.3.dist-info/WHEEL
bigninja-0.0.3.dist-info/top_level.txt
bigninja-0.0.3.dist-info/RECORD
