Metadata-Version: 2.1
Name: bigninja
Version: 0.0.3
Summary: pyspark helpers
Home-page: https://github.com/aloneguid/bigninja
Author: Ivan Gavryliuk
Author-email: aloneguid@outlook.com
License: Apache-2.0
Platform: UNKNOWN
